README.txt
setup.cfg
setup.py
docs/HISTORY.txt
docs/INSTALL.txt
docs/LICENSE.GPL
docs/LICENSE.txt
easyshop/__init__.py
easyshop.stocks.egg-info/PKG-INFO
easyshop.stocks.egg-info/SOURCES.txt
easyshop.stocks.egg-info/dependency_links.txt
easyshop.stocks.egg-info/entry_points.txt
easyshop.stocks.egg-info/namespace_packages.txt
easyshop.stocks.egg-info/not-zip-safe
easyshop.stocks.egg-info/requires.txt
easyshop.stocks.egg-info/top_level.txt
easyshop/stocks/__init__.py
easyshop/stocks/configure.zcml
easyshop/stocks/events.py
easyshop/stocks/profiles.zcml
easyshop/stocks/adapters/__init__.py
easyshop/stocks/adapters/configure.zcml
easyshop/stocks/adapters/data.py
easyshop/stocks/adapters/stock_management.py
easyshop/stocks/browser/__init__.py
easyshop/stocks/browser/configure.zcml
easyshop/stocks/browser/stock_information_container_view.pt
easyshop/stocks/browser/stock_information_container_view.py
easyshop/stocks/browser/stock_information_view.pt
easyshop/stocks/browser/stock_information_view.py
easyshop/stocks/content/__init__.py
easyshop/stocks/content/stock_information.py
easyshop/stocks/content/stock_information_container.py
easyshop/stocks/portlets/__init__.py
easyshop/stocks/portlets/configure.zcml
easyshop/stocks/portlets/stock_information.pt
easyshop/stocks/portlets/stock_information.py
easyshop/stocks/profiles/default/factorytool.xml
easyshop/stocks/profiles/default/portlets.xml
easyshop/stocks/profiles/default/types.xml
easyshop/stocks/profiles/default/workflows.xml
easyshop/stocks/profiles/default/types/StockInformation.xml
easyshop/stocks/profiles/default/types/StockInformationContainer.xml